lib/__init__.py
lib/aifunc.py
lib/config.py
lib/function_wrapper.py
lib/llm.py
lib/omnilog.py
lib/set_store.py
lib/util.py
lib/functions/__init__.py
lib/functions/apply_code_diff_to_file.py
lib/functions/browser.py
lib/functions/calculate.py
lib/functions/cat_file.py
lib/functions/change_working_directory.py
lib/functions/clear_screen.py
lib/functions/create_github_repo.py
lib/functions/exit.py
lib/functions/filesystem.py
lib/functions/get_api_model_config.py
lib/functions/get_project_files.py
lib/functions/git_branch.py
lib/functions/git_commit_and_push.py
lib/functions/git_diff.py
lib/functions/git_pull.py
lib/functions/git_pull_request.py
lib/functions/git_stash.py
lib/functions/git_status.py
lib/functions/help.py
lib/functions/install_package.py
lib/functions/llm_write_code.py
lib/functions/manage_app_container.py
lib/functions/manage_github_issues.py
lib/functions/manage_mitta_shell_container.py
lib/functions/ping.py
lib/functions/reverse_code_diff.py
lib/functions/run_python_file.py
lib/functions/scan_html_code.py
lib/functions/scan_python_code.py
lib/functions/search.py
lib/functions/search_file.py
lib/functions/set_github_token.py
lib/functions/speak.py
lib/functions/write_code_to_file.py
webwright/__init__.py
webwright/main.py
webwright-0.0.7.dist-info/LICENSE
webwright-0.0.7.dist-info/METADATA
webwright-0.0.7.dist-info/WHEEL
webwright-0.0.7.dist-info/entry_points.txt
webwright-0.0.7.dist-info/top_level.txt
webwright-0.0.7.dist-info/RECORD
