Metadata-Version: 2.1
Name: webwright
Version: 0.0.7
Summary: Webwright: The Ghost in Your Shell 👻💻
Home-page: https://github.com/MittaAI/webwright
Author: Kord Campbell
Author-email: kordless@gmail.com
License: MIT
Keywords: ai terminal shell automation development tools
Classifier: Development Status :: 3 - Alpha
Classifier: Intended Audience :: Developers
Classifier: Intended Audience :: System Administrators
Classifier: License :: OSI Approved :: MIT License
Classifier: Programming Language :: Python :: 3
Classifier: Programming Language :: Python :: 3.7
Classifier: Programming Language :: Python :: 3.8
Classifier: Programming Language :: Python :: 3.9
Classifier: Programming Language :: Python :: 3.10
Classifier: Topic :: Software Development :: Libraries :: Python Modules
Classifier: Topic :: System :: Shells
Classifier: Topic :: Utilities
License-File: LICENSE
Requires-Dist: gitpython
Requires-Dist: prompt-toolkit
Requires-Dist: beautifulsoup4
Requires-Dist: coolname
Requires-Dist: pygments
Requires-Dist: openai
Requires-Dist: openai[datalib]
Requires-Dist: tenacity
Requires-Dist: anthropic
Requires-Dist: torch
Requires-Dist: transformers
Requires-Dist: sentence-transformers ==2.2.2
Requires-Dist: InstructorEmbedding
Requires-Dist: Halo
Requires-Dist: PyGithub
Requires-Dist: cowsay
Requires-Dist: google-generativeai
Requires-Dist: unidiff
Requires-Dist: patch
Requires-Dist: chromadb ==0.5.5
Requires-Dist: playsound
